my_adder-0.1.data/scripts/my-adder
src/__init__.py
my_adder-0.1.dist-info/METADATA
my_adder-0.1.dist-info/WHEEL
my_adder-0.1.dist-info/top_level.txt
my_adder-0.1.dist-info/RECORD
