Metadata-Version: 2.1
Name: my-adder
Version: 0.1
Summary: A Docker and AWS utility package
Home-page: https://github.com/
Author: Sachin Goya;
Author-email: deepak.kumar.iet@gmail.com
Classifier: Programming Language :: Python :: 3
